app/blueprint_graphql.py
app/blueprint_haystack.py
app/graphql_model.py
app/haystack_schema.json
app/main.py
app/schema_graphql.py
app/haystackui/index.html
app/haystackui/index.js
app/haystackui/router.js
app/haystackui/store.js
app/haystackui/components/CChart/CChart.js
app/haystackui/components/CEntityRow/CEntityRow.css
app/haystackui/components/CEntityRow/CEntityRow.js
app/haystackui/components/CFilterApiBlock/CFilterApiBlock.css
app/haystackui/components/CFilterApiBlock/CFilterApiBlock.js
app/haystackui/components/CGraph/CGraph.js
app/haystackui/plugins/customPlugin.js
app/haystackui/presenters/PHisDataTable/PHisDataTable.js
app/haystackui/services/dateUtils.js
app/haystackui/services/formatChartService.js
app/haystackui/services/formatEntityService.js
app/haystackui/services/haystackApi.service.js
app/haystackui/services/index.js
app/haystackui/services/utils.js
app/haystackui/views/VMainLayout/VMainLayout.css
app/haystackui/views/VMainLayout/VMainLayout.js
app/haystackui/views/VSummaryContent/VSummaryContent.css
app/haystackui/views/VSummaryContent/VSummaryContent.js
app/static/favicon.ico
shaystack/__init__.py
shaystack/csvdumper.py
shaystack/csvparser.py
shaystack/datatypes.py
shaystack/dumper.py
shaystack/empty_grid.py
shaystack/exception.py
shaystack/filter_ast.py
shaystack/grid.py
shaystack/grid_diff.py
shaystack/grid_filter.py
shaystack/haysondumper.py
shaystack/haysonparser.py
shaystack/haystack_units.pint
shaystack/haystack_units_mapping.txt
shaystack/jsondumper.py
shaystack/jsonparser.py
shaystack/metadata.py
shaystack/ops.py
shaystack/parser.py
shaystack/period.py
shaystack/pintutil.py
shaystack/sortabledict.py
shaystack/tools.py
shaystack/triodumper.py
shaystack/trioparser.py
shaystack/type.py
shaystack/version.py
shaystack/zincdumper.py
shaystack/zincparser.py
shaystack/zoneinfo.py
shaystack/providers/__init__.py
shaystack/providers/athena.py
shaystack/providers/db.py
shaystack/providers/db_haystack_interface.py
shaystack/providers/db_mongo.py
shaystack-0.10.2.dist-info/AUTHORS
shaystack-0.10.2.dist-info/LICENSE
shaystack-0.10.2.dist-info/METADATA
shaystack-0.10.2.dist-info/WHEEL
shaystack-0.10.2.dist-info/entry_points.txt
shaystack-0.10.2.dist-info/pbr.json
shaystack-0.10.2.dist-info/top_level.txt
shaystack-0.10.2.dist-info/RECORD
