Metadata-Version: 2.1
Name: shaystack
Version: 0.10.2
Summary: Implementation of Haystack Project Specification
Home-page: https://github.com/engie-group/shaystack
Author: Philippe PRADOS
Author-email: support@prados.fr
License: BSD
Project-URL: Bug Tracker, https://github.com/engie-group/shaystack/issues
Project-URL: Documentation, https://engie-group.github.io/shaystack/
Project-URL: Source Code, https://github.com/engie-group/shaystack
Keywords: haystack
Platform: UNKNOWN
Classifier: Development Status :: 4 - Beta
Classifier: Environment :: Web Environment
Classifier: Intended Audience :: Developers
Classifier: License :: OSI Approved :: BSD License
Classifier: Programming Language :: Python
Classifier: Programming Language :: Python :: 3.7
Classifier: Programming Language :: Python :: 3.8
Classifier: Programming Language :: Python :: 3.9
Classifier: Topic :: Scientific/Engineering
Classifier: Topic :: Scientific/Engineering :: Information Analysis
Classifier: Topic :: Software Development :: Libraries :: Python Modules
Requires-Dist: pyparsing (==2.4.7)
Requires-Dist: pytz (==2021.1)
Requires-Dist: iso8601 (==0.1.14)
Requires-Dist: six (~=1.16.0)
Requires-Dist: accept-types
Requires-Dist: overrides (==6.0.0)
Requires-Dist: tzlocal (==2.1)
Requires-Dist: pint (==0.17)
Requires-Dist: click (>=8.0)
Provides-Extra: dev
Requires-Dist: python-dotenv ; extra == 'dev'
Requires-Dist: zappa (==0.54.2) ; extra == 'dev'
Requires-Dist: ninja (>=1.10.0) ; extra == 'dev'
Requires-Dist: mypy (>=0.900) ; extra == 'dev'
Requires-Dist: flake8 (==3.9.1) ; extra == 'dev'
Requires-Dist: itsdangerous (==2.0.1) ; extra == 'dev'
Requires-Dist: Jinja2 (>=2.11.9) ; extra == 'dev'
Requires-Dist: pylint (==2.8.2) ; extra == 'dev'
Requires-Dist: pytest (>=7.0.0) ; extra == 'dev'
Requires-Dist: twine (==3.4.1) ; extra == 'dev'
Requires-Dist: mock (==4.0.3) ; extra == 'dev'
Requires-Dist: coverage (==5.5) ; extra == 'dev'
Requires-Dist: psycopg2 (>=2.9) ; extra == 'dev'
Requires-Dist: PyMySQL (==1.0.2) ; extra == 'dev'
Requires-Dist: pymongo (==3.11.4) ; extra == 'dev'
Requires-Dist: pdoc3 (==0.9.2) ; extra == 'dev'
Requires-Dist: pip-licenses ; extra == 'dev'
Requires-Dist: types-pytz ; extra == 'dev'
Requires-Dist: types-click ; extra == 'dev'
Requires-Dist: boto3-stubs ; extra == 'dev'
Requires-Dist: pymongo-stubs ; extra == 'dev'
Requires-Dist: types-Flask-Cors ; extra == 'dev'
Requires-Dist: graphene-stubs ; extra == 'dev'
Requires-Dist: types-PyMySQL ; extra == 'dev'
Requires-Dist: types-mock ; extra == 'dev'
Requires-Dist: types-Flask ; extra == 'dev'
Requires-Dist: types-tzlocal ; extra == 'dev'
Requires-Dist: types-python-dateutil ; extra == 'dev'
Requires-Dist: types-six ; extra == 'dev'
Requires-Dist: types-requests ; extra == 'dev'
Requires-Dist: types-psycopg2 ; extra == 'dev'
Provides-Extra: flask
Requires-Dist: flask (==2.1.0) ; extra == 'flask'
Requires-Dist: flask-cors (==3.0.10) ; extra == 'flask'
Requires-Dist: itsdangerous (==2.0.1) ; extra == 'flask'
Requires-Dist: Jinja2 (>=2.11.9) ; extra == 'flask'
Provides-Extra: graphql
Requires-Dist: flask (==2.1.0) ; extra == 'graphql'
Requires-Dist: flask-cors (==3.0.10) ; extra == 'graphql'
Requires-Dist: graphene (==3.0) ; extra == 'graphql'
Requires-Dist: graphql-server (==3.0.0b4) ; extra == 'graphql'
Requires-Dist: promise (==2.3) ; extra == 'graphql'
Provides-Extra: lambda
Requires-Dist: flask (==2.1.0) ; extra == 'lambda'
Requires-Dist: flask-cors (==3.0.10) ; extra == 'lambda'
Requires-Dist: itsdangerous (==2.0.1) ; extra == 'lambda'
Requires-Dist: Jinja2 (>=2.11.9) ; extra == 'lambda'
Requires-Dist: zappa ; extra == 'lambda'
